AUTHORS
LICENSE
MANIFEST.in
setup.py
pycorreios/__init__.py
pycorreios/correios.py
pycorreios/model.py
pycorreios.egg-info/PKG-INFO
pycorreios.egg-info/SOURCES.txt
pycorreios.egg-info/dependency_links.txt
pycorreios.egg-info/pbr.json
pycorreios.egg-info/top_level.txt
test/test_correios.py