Metadata-Version: 1.1
Name: pycorreios
Version: 0.1.2
Summary: API for correios in Python
Home-page: https://github.com/avelino/pycorreios/
Author: Thiago Avelino
Author-email: thiagoavelinoster@gmail.com
License: MIT
Platform: any
Classifier: Development Status :: 4 - Beta
Classifier: Intended Audience :: Developers
Classifier: License :: OSI Approved :: MIT License
Classifier: Operating System :: OS Independent
Classifier: Programming Language :: Python
Classifier: Topic :: Software Development :: Libraries :: Python Modules
